sqla_fancy_core/__init__.py
sqla_fancy_core/builders.py
sqla_fancy_core/decorators.py
sqla_fancy_core/errors.py
sqla_fancy_core/wrappers.py
sqla_fancy_core-5.0.0.dist-info/METADATA
sqla_fancy_core-5.0.0.dist-info/WHEEL
sqla_fancy_core-5.0.0.dist-info/licenses/LICENSE
sqla_fancy_core-5.0.0.dist-info/RECORD
