Metadata-Version: 2.4
Name: sqla-fancy-core
Version: 5.0.0
Summary: A collection of type-safe, async friendly, and un-opinionated enhancements to SQLAlchemy Core that works well with mordern web servers.
Project-URL: Homepage, https://github.com/sayanarijit/sqla-fancy-core
Author-email: Arijit Basu <sayanarijit@gmail.com>
Maintainer-email: Arijit Basu <sayanarijit@gmail.com>
License: MIT License
License-File: LICENSE
Keywords: async,database,fastapi,orm,sql,sqlalchemy,type-safe,web
Classifier: Intended Audience :: Developers
Classifier: License :: OSI Approved :: MIT License
Classifier: Programming Language :: Python :: 3
Requires-Python: >=3.10
Requires-Dist: sqlalchemy<3.0.0,>=2.0.0
Provides-Extra: dev
Requires-Dist: aiosqlite; extra == 'dev'
Requires-Dist: asyncpg; extra == 'dev'
Requires-Dist: build; extra == 'dev'
Requires-Dist: fastapi; extra == 'dev'
Requires-Dist: flake8; extra == 'dev'
Requires-Dist: hatchling; extra == 'dev'
Requires-Dist: httpx; extra == 'dev'
Requires-Dist: ipython; extra == 'dev'
Requires-Dist: psycopg2-binary; extra == 'dev'
Requires-Dist: pydantic; extra == 'dev'
Requires-Dist: pytest; extra == 'dev'
Requires-Dist: pytest-asyncio; extra == 'dev'
Requires-Dist: python-multipart; extra == 'dev'
Requires-Dist: sqlalchemy[asyncio]; extra == 'dev'
Requires-Dist: twine; extra == 'dev'
